gradient_metrics/__init__.py
gradient_metrics/general.py
gradient_metrics/metrics.py
gradient_metrics-0.5.0.dist-info/LICENSE
gradient_metrics-0.5.0.dist-info/METADATA
gradient_metrics-0.5.0.dist-info/WHEEL
gradient_metrics-0.5.0.dist-info/RECORD
