Metadata-Version: 2.1
Name: gradient_metrics
Version: 0.5.0
Summary: Neural Network Gradient Metrics with PyTorch
Home-page: https://github.com/RonMcKay/gradient_metrics
License: MIT
Author: Philipp Oberdiek
Author-email: git@oberdiek.net
Requires-Python: >=3.8,<3.12
Classifier: License :: OSI Approved :: MIT License
Classifier: Programming Language :: Python :: 3
Classifier: Programming Language :: Python :: 3.8
Classifier: Programming Language :: Python :: 3.9
Classifier: Programming Language :: Python :: 3.10
Classifier: Programming Language :: Python :: 3.11
Requires-Dist: torch (>=2.0.0,<3.0.0)
Project-URL: Documentation, https://ronmckay.github.io/gradient_metrics/
Project-URL: Repository, https://github.com/RonMcKay/gradient_metrics
